betsy_ros/__init__.py
betsy_ros/_version.py
betsy_ros/environment.py
betsy_ros/interfaces.py
betsy_ros/packages.py
betsy_ros/workspace.py
betsy_ros-0.2.1.dist-info/METADATA
betsy_ros-0.2.1.dist-info/WHEEL
betsy_ros-0.2.1.dist-info/licenses/LICENSE
betsy_ros-0.2.1.dist-info/RECORD
