Metadata-Version: 2.4
Name: betsy_ros
Version: 0.2.1
Summary: In this time of revolution between the regimes of ROS 1 and ROS 2, Betsy ROS creates a unified banner.
Project-URL: Homepage, https://github.com/MetroRobots/betsy_ros
Project-URL: Bug Tracker, https://github.com/MetroRobots/betsy_ros/issues
Author-email: "David V. Lu!!" <davidvlu@gmail.com>
Maintainer-email: "David V. Lu!!" <davidvlu@gmail.com>
License-File: LICENSE
Classifier: Development Status :: 4 - Beta
Classifier: License :: OSI Approved :: BSD License
Classifier: Programming Language :: Python :: 3 :: Only
Classifier: Programming Language :: Python :: 3.8
Classifier: Topic :: Software Development
Requires-Python: >=3.8
